{"globalvars": ["_ZN10__cxxabiv119__terminate_handlerE", "_ZSt7nothrow", "_ZN10__cxxabiv120__unexpected_handlerE"], "importedglobals": ["_Ux86_local_addr_space", "__sF", "_UPT_accessors"], "importedfunctions": ["_Ux86_init_local", "pthread_key_delete", "sprintf", "_Ux86_step", "pthread_once", "pthread_mutex_unlock", "_Ux86_init_remote", "strcmp", "strlen", "pthread_mutex_lock", "_UPT_create", "__stack_chk_fail", "pthread_setspecific", "free", "realloc", "fwrite", "_Ux86_create_addr_space", "memcpy", "_UPT_destroy", "fputs", "_Ux86_get_reg", "dl_iterate_phdr", "pthread_getspecific", "fputc", "memcmp", "_Ux86_set_caching_policy", "abort", "write", "_Ux86_get_proc_name_by_ip", "malloc", "pthread_key_create"], "exportedfunctions": ["_ZN10__cxxabiv119__foreign_exceptionD0Ev", "_ZNSt9exceptionD1Ev", "_ZN10__cxxabiv115__forced_unwindD0Ev", "_ZdlPv", "_ZN10__cxxabiv115__forced_unwindD1Ev", "_ZN10__cxxabiv119__foreign_exceptionD1Ev", "_ZNK10__cxxabiv117__class_type_info10__do_catchEPKSt9type_infoPPvj", "__gxx_personality_v0", "__deregister_frame_info_bases", "_ZN10__cxxabiv115__forced_unwindD2Ev", "_Unwind_GetGR", "_ZN11crashlytics8envelope14unwind_contextC1EP14unw_addr_space", "__register_frame_info_bases", "_ZSt9terminatev", "function_name_from_ptrace_context", "_ZNKSt13bad_exception4whatEv", "_Unwind_Resume_or_Rethrow", "_ZNK10__cxxabiv117__class_type_info20__do_find_public_srcEiPKvPKS0_S2_", "_ZSt15set_new_handlerPFvvE", "_ZN10__cxxabiv120__si_class_type_infoD2Ev", "function_name_from_ucontext", "_ZN11crashlytics8envelope14unwind_contextD2Ev", "_ZN10__cxxabiv119__foreign_exceptionD2Ev", "__gcclibcxx_demangle_callback", "_Unwind_SetGR", "_ZNK11crashlytics8envelope14unwind_context13address_spaceEv", "_Unwind_GetDataRelBase", "_ZSt10unexpectedv", "_ZNK10__cxxabiv117__class_type_info12__do_dyncastEiNS0_10__sub_kindEPKS0_PKvS3_S5_RNS0_16__dyncast_resultE", "_ZNSt13bad_exceptionD1Ev", "_ZNSt9exceptionD2Ev", "_ZN10__cxxabiv117__class_type_infoD1Ev", "_ZNK10__cxxabiv117__class_type_info11__do_upcastEPKS0_PKvRNS0_15__upcast_resultE", "__register_frame_table", "_ZN10__cxxabiv111__terminateEPFvvE", "__frame_state_for", "_ZN10__cxxabiv117__class_type_infoD0Ev", "_Unwind_Find_FDE", "_ZSt18uncaught_exceptionv", "_Unwind_SetIP", "_ZN11crashlytics8envelope6detail14managed_cursorD2Ev", "_ZSt13set_terminatePFvvE", "_ZSt14set_unexpectedPFvvE", "_Unwind_Backtrace", "_ZN11crashlytics8envelope14unwind_contextC2EP14unw_addr_space", "__deregister_frame_info", "_ZNSt9bad_allocD2Ev", "_ZN11crashlytics8envelope6detail14managed_cursorD1Ev", "_Unwind_FindEnclosingFunction", "_Unwind_Resume", "__register_frame_info", "_ZN11crashlytics8envelope14unwind_contextD1Ev", "_ZNSt13bad_exceptionD2Ev", "_Unwind_ForcedUnwind", "_Znwj", "_ZNK10__cxxabiv117__class_type_info11__do_upcastEPKS0_PPv", "unwind_ptrace", "_ZNSt9exceptionD0Ev", "_ZN10__cxxabiv117__class_type_infoD2Ev", "_Unwind_GetTextRelBase", "_Unwind_GetIPInfo", "_ZNKSt9bad_alloc4whatEv", "_ZN10__cxxabiv112__unexpectedEPFvvE", "_Unwind_RaiseException", "_ZNSt9bad_allocD1Ev", "_Unwind_DeleteException", "_ZN10__cxxabiv120__si_class_type_infoD1Ev", "_ZN9__gnu_cxx27__verbose_terminate_handlerEv", "context", "_ZN11crashlytics8envelope6detail14managed_cursorC2Ev", "_ZNSt13bad_exceptionD0Ev", "_ZNKSt9exception4whatEv", "_Unwind_GetCFA", "_Unwind_GetRegionStart", "__register_frame", "__register_frame_info_table", "unwind", "__register_frame_info_table_bases", "_Unwind_GetIP", "__deregister_frame", "_Unwind_GetLanguageSpecificData", "_ZN10__cxxabiv120__si_class_type_infoD0Ev", "_ZNSt9bad_allocD0Ev", "_ZN11crashlytics8envelope6detail14managed_cursorC1Ev"], "allstrings": ["__gnu_cxx::__concurrence_lock_error", "__gnu_cxx::__concurrence_unlock_error", "deleted virtual method called\n", "terminate called after throwing an instance of '", "terminate called without an active exception\n", "std::basic_string<char, std::char_traits<char>, std::allocator<char> >", "std::basic_istream<char, std::char_traits<char> >", "std::basic_ostream<char, std::char_traits<char> >", "std::basic_iostream<char, std::char_traits<char> >", "N9__gnu_cxx24__concurrence_lock_errorE", "N9__gnu_cxx26__concurrence_unlock_errorE", "std::bad_alloc", "std::exception", "std::bad_exception", "pure virtual method called\n", "terminate called recursively\n", "  what():  ", "_GLOBAL_", "(anonymous namespace)", "string literal", "auto", "[abi:", "{default arg#", "JArray", "vtable for ", "VTT for ", "construction vtable for ", "-in-", "typeinfo for ", "typeinfo name for ", "typeinfo fn for ", "non-virtual thunk to ", "virtual thunk to ", "covariant return thunk to ", "java Class for ", "guard variable for ", "TLS init function for ", "TLS wrapper function for ", "reference temporary #", " for ", "hidden alias for ", "transaction clone for ", "non-transaction clone for ", "_Sat ", "_Accum", "_Fract", "operator", "operator ", "new ", "false", "true", "java resource ", "decltype (", "this", "{parm#", "global constructors keyed to ", "global destructors keyed to ", "{lambda(", "{unnamed type#", " [clone ", " restrict", " volatile", " const", "complex ", "imaginary ", " __vector(", "std::allocator", "allocator", "std::basic_string", "basic_string", "std::string", "std::istream", "basic_istream", "std::ostream", "basic_ostream", "std::iostream", "basic_iostream", "alignof ", "const_cast", "delete[] ", "dynamic_cast", "delete ", "operator\"\" ", "new[]", "reinterpret_cast", "static_cast", "sizeof ", "throw", "throw ", "signed char", "bool", "boolean", "char", "byte", "double", "long double", "float", "__float128", "unsigned char", "unsigned int", "unsigned", "long", "unsigned long", "__int128", "unsigned __int128", "short", "unsigned short", "void", "wchar_t", "long long", "unsigned long long", "decimal32", "decimal64", "decimal128", "half", "char16_t", "char32_t", "decltype(nullptr)", "St9bad_alloc", "N10__cxxabiv120__si_class_type_infoE", "N10__cxxabiv117__class_type_infoE", "St9exception", "St13bad_exception", "N10__cxxabiv115__forced_unwindE", "N10__cxxabiv119__foreign_exceptionE", "St9type_info"], "stringidentifiers": ["__gnu_cxx::__concurrence_lock_error", "__gnu_cxx::__concurrence_unlock_error", "N9__gnu_cxx24__concurrence_lock_errorE", "N9__gnu_cxx26__concurrence_unlock_errorE", "std::bad_alloc", "std::exception", "std::bad_exception", "_GLOBAL_", "auto", "JArray", "_Accum", "_Fract", "operator", "false", "true", "this", "std::allocator", "allocator", "std::basic_string", "basic_string", "std::string", "std::istream", "basic_istream", "std::ostream", "basic_ostream", "std::iostream", "basic_iostream", "const_cast", "dynamic_cast", "reinterpret_cast", "static_cast", "throw", "bool", "boolean", "char", "byte", "double", "float", "__float128", "unsigned", "long", "__int128", "short", "void", "wchar_t", "decimal32", "decimal64", "decimal128", "half", "char16_t", "char32_t", "St9bad_alloc", "N10__cxxabiv120__si_class_type_infoE", "N10__cxxabiv117__class_type_infoE", "St9exception", "St13bad_exception", "N10__cxxabiv115__forced_unwindE", "N10__cxxabiv119__foreign_exceptionE", "St9type_info"], "debugstrings": ["GCC: (GNU) 4.8"], "localsymbols": [""], "dependencies": ["libm.so", "libc.so", "libdl.so", "libunwind.so", "liblog.so", "libunwind-ptrace.so", "libstdc++.so"], "elfname": "libcrashlytics-envelope.so"}