{"globalvars": ["__popcount_tab", "__INIT_ARRAY__", "__FINI_ARRAY__"], "importedglobals": ["__stack_chk_guard"], "importedfunctions": ["__stack_chk_fail", "free", "open", "memchr", "close", "pthread_once", "__errno", "read", "malloc"], "exportedfunctions": ["_Z29get_android_processor_supportv", "android_getCpuFeatures", "Java_io_card_payment_CardScanner_nUseTegra", "__popcountsi2", "_Z17dmz_use_gles_warpv", "_Z37_DMZ_7b98a240b2f189810bc0e7a25db658a5v", "android_setCpu", "_Z17dmz_set_gles_warpi", "_Z37_DMZ_34b1224dc131d7e7469c3ac448f90e73v", "android_getCpuFamily", "Java_io_card_payment_CardScanner_nUseNeon", "JNI_OnLoad", "android_getCpuCount"], "allstrings": ["/proc/cpuinfo", "/sys/devices/system/cpu/present", "/sys/devices/system/cpu/possible"], "stringidentifiers": [], "debugstrings": ["GCC: (GNU) 4.6 20120106 (prerelease)"], "localsymbols": [""], "dependencies": ["libm.so", "libstdc++.so", "libc.so", "liblog.so", "libdl.so"], "elfname": "libcardioDecider.so"}