{"globalvars": [], "importedglobals": [], "importedfunctions": ["memcpy", "__stack_chk_fail", "malloc", "free"], "exportedfunctions": ["JNI_OnLoad"], "allstrings": ["could not allocate memory", "java/lang/RuntimeException", "nativeAllocate", "(I)J", "nativeFree", "(J)V", "nativeCopyToByteArray", "(J[BII)V", "nativeCopyFromByteArray", "nativeMemcpy", "(JJI)V", "nativeReadByte", "(J)B", "com/facebook/imagepipeline/memory/NativeMemoryChunk"], "stringidentifiers": ["nativeAllocate", "nativeFree", "nativeCopyToByteArray", "nativeCopyFromByteArray", "nativeMemcpy", "nativeReadByte"], "debugstrings": ["GCC: (GNU) 4.6 20120106 (prerelease)", "GCC: (GNU) 4.8"], "localsymbols": [""], "dependencies": ["libdl.so", "libc.so", "libm.so", "libstdc++.so"], "elfname": "libmemchunk.so"}