{"globalvars": ["_ULarm_local_addr_space", "_UIarm_debug_level", "_UPT_accessors", "_Uarm_local_addr_space", "_UPT_reg_offset"], "importedglobals": ["__stack_chk_guard", "__sF"], "importedfunctions": ["getpagesize", "close", "__stack_chk_fail", "free", "getpid", "fopen", "mmap", "pthread_rwlock_wrlock", "raise", "strcat", "pthread_rwlock_init", "strlen", "__android_log_print", "open", "realloc", "abort", "setbuf", "strncmp", "memmove", "pthread_rwlock_rdlock", "strcmp", "read", "ptrace", "memset", "pthread_once", "fseek", "getenv", "munmap", "strcpy", "qsort", "strncpy", "memcpy", "strdup", "fstat", "atoi", "fread", "fclose", "memchr", "calloc", "dl_iterate_phdr", "sigfillset", "pthread_rwlock_unlock", "memcmp", "malloc", "strrchr", "__errno"], "exportedfunctions": ["_Uarm_is_signal_frame", "restore_core_regs", "_ULarm_get_proc_name", "_Unwind_RaiseException", "__gnu_Unwind_RaiseException", "map_local_is_readable", "_UPT_access_mem", "_Uarm_create_addr_space", "_Uarm_is_fpreg", "unw_map_local_cursor_get_next", "_Unwind_Complete", "_ULarm_dwarf_search_unwind_table", "_ULarm_set_fpreg", "_Uarm_dwarf_find_unwind_table", "_Uarm_step", "_Uarm_flush_cache", "_ULarm_create_addr_space", "___Unwind_Resume", "_UPT_resume", "_ULarm_dwarf_find_unwind_table", "_Uarm_get_proc_name_by_ip", "_Unwind_GetDataRelBase", "__gnu_Unwind_Restore_VFP_D_16_to_31", "__gnu_Unwind_Restore_VFP_D", "_ULarm_handle_signal_frame", "_ULarm_is_signal_frame", "__udivsi3", "map_local_get_image_name", "_UPT_get_dyn_info_list_addr", "_UPT_get_proc_name", "unw_map_cursor_create", "__gnu_Unwind_Save_VFP_D", "_U_dyn_cancel", "map_local_is_writable", "_UPT_find_proc_info", "_ULarm_get_proc_name_by_ip", "_Unwind_Resume", "__gnu_unwind_execute", "_Unwind_GetRegionStart", "_ULarm_set_reg", "_Unwind_VRS_Pop", "_Unwind_VRS_Set", "_Uarm_getcontext", "_ULarm_resume", "_Uarm_get_elf_image", "_Uarm_get_fpreg", "__gnu_Unwind_Restore_WMMXD", "_Unwind_ForcedUnwind", "_Uarm_set_caching_policy", "_ULarm_dwarf_find_debug_frame", "_Uarm_strerror", "_Unwind_DeleteException", "_UPT_access_reg", "_Uarm_init_remote", "_Unwind_GetLanguageSpecificData", "___Unwind_RaiseException", "__gnu_unwind_frame", "_ULarm_search_unwind_table", "_Uarm_search_unwind_table", "_Uarm_get_save_loc", "_Unwind_Resume_or_Rethrow", "_Uarm_get_proc_info", "__gnu_Unwind_Save_WMMXD", "local_get_elf_image", "_Unwind_VRS_Get", "unw_map_cursor_reset", "_UPT_destroy", "_ULarm_init_local", "_ULarm_get_proc_info", "_Uarm_get_proc_info_by_ip", "unw_map_local_destroy", "___Unwind_ForcedUnwind", "_ULarm_init_remote", "_Uarm_handle_signal_frame", "_Uelf32_memory_read", "__restore_core_regs", "unw_backtrace", "unw_map_set", "_ULarm_get_save_loc", "_Uarm_regname", "unw_map_cursor_clear", "_UPT_create", "__divsi3", "_U_dyn_info_list_addr", "_Uarm_set_fpreg", "unw_map_local_cursor_get", "__gnu_Unwind_Resume_or_Rethrow", "_Unwind_GetTextRelBase", "unw_map_cursor_destroy", "_Unwind_Backtrace", "_Uarm_get_reg", "_UPT_access_fpreg", "_ULarm_get_proc_info_by_ip", "unw_map_local_create", "_Uarm_set_reg", "_Uarm_dwarf_find_debug_frame", "__gnu_Unwind_Restore_VFP", "_ULarm_get_reg", "_UPT_put_unwind_info", "_Uarm_get_accessors", "_ULarm_set_caching_policy", "_Uarm_get_proc_name", "___Unwind_Resume_or_Rethrow", "_Uarm_local_access_addr_space_init", "_ULarm_destroy_addr_space", "_Uarm_resume", "unw_map_cursor_get_next", "_Uarm_dwarf_search_unwind_table", "_ULarm_local_access_addr_space_init", "_ULarm_step", "__gnu_Unwind_Save_WMMXC", "__gnu_Unwind_Restore_WMMXC", "__gnu_Unwind_Save_VFP", "unw_map_local_cursor_valid", "_Uarm_init_local", "_Unwind_GetCFA", "__gnu_Unwind_Save_VFP_D_16_to_31", "__gnu_Unwind_Backtrace", "_U_dyn_register", "__gnu_Unwind_Resume", "___Unwind_Backtrace", "_Uarm_destroy_addr_space", "_ULarm_get_fpreg"], "allstrings": ["UNW_DEBUG_LEVEL", "no error", "unspecified (general) error", "out of memory", "bad register number", "attempt to write read-only register", "stop unwinding", "invalid IP", "bad frame", "unsupported operation or bad value", "unwind info has unsupported version", "no unwind info found", "invalid error code", "libunwind", "%s: ip and cfa unchanged; stopping here (ip=0x%lx)\n", ".debug_frame", ".gnu_debuglink", ".gnu_debugdata", ".text", "/.debug/", "/usr/lib/debug", "/dev/", "ashmem/", "/proc/", "/maps", "[stack:", "wCGR0", "wCGR1", "wCGR2", "wCGR3", "wCGR4", "wCGR5", "wCGR6", "wCGR7", "spsr", "spsr_fiq", "spsr_irq", "spsr_abt", "spsr_und", "spsr_svc", "r8_usr", "r9_usr", "r10_usr", "r11_usr", "r12_usr", "r13_usr", "r14_usr", "r8_fiq", "r9_fiq", "r10_fiq", "r11_fiq", "r12_fiq", "r13_fiq", "r14_fiq", "r13_irq", "r14_irq", "r13_abt", "r14_abt", "r13_und", "r14_und", "r13_svc", "r14_svc", "UNW_ARM_UNWIND_METHOD", "@@HHPPXX", "apply_reg_state", "@@HHPPXX", "apply_reg_state", "_Uarm_step", "_ULarm_step"], "stringidentifiers": ["UNW_DEBUG_LEVEL", "libunwind", "wCGR0", "wCGR1", "wCGR2", "wCGR3", "wCGR4", "wCGR5", "wCGR6", "wCGR7", "spsr", "spsr_fiq", "spsr_irq", "spsr_abt", "spsr_und", "spsr_svc", "r8_usr", "r9_usr", "r10_usr", "r11_usr", "r12_usr", "r13_usr", "r14_usr", "r8_fiq", "r9_fiq", "r10_fiq", "r11_fiq", "r12_fiq", "r13_fiq", "r14_fiq", "r13_irq", "r14_irq", "r13_abt", "r14_abt", "r13_und", "r14_und", "r13_svc", "r14_svc", "UNW_ARM_UNWIND_METHOD", "apply_reg_state", "apply_reg_state", "_Uarm_step", "_ULarm_step"], "debugstrings": ["unwind info has unsupported version", "GCC: (GNU) 4.9 20150123 (prerelease)"], "localsymbols": [""], "dependencies": ["libstdc++.so", "liblog.so", "libm.so", "libc.so", "libdl.so"], "elfname": "libunwind-crashlytics.so"}