{"globalvars": ["VP8GetCPUInfo"], "importedglobals": [], "importedfunctions": ["calloc", "pthread_mutex_unlock", "pow", "pthread_mutex_destroy", "pthread_cond_signal", "memcmp", "malloc", "pthread_cond_destroy", "pthread_cond_init", "pthread_mutex_lock", "pthread_create", "__memcpy_chk", "memcpy", "free", "log10", "pthread_mutex_init", "memset", "qsort", "pthread_cond_wait", "__stack_chk_fail", "memmove", "log", "pthread_join"], "exportedfunctions": ["WebPDecodeRGBInto", "WebPIDecGetYUVA", "WebPPictureImportRGBX", "WebPPictureRescale", "WebPIDecGetRGB", "VP8LCheckSignature", "WebPEncodeLosslessRGBA", "WebPEncodeRGB", "WebPGetWorkerInterface", "WebPIDecode", "WebPSetWorkerInterface", "WebPEncodeBGR", "WebPCopyPixels", "WebPSafeFree", "WebPGetColorPalette", "WebPPictureHasTransparency", "WebPBlendAlpha", "WebPEncodeLosslessBGR", "WebPPictureDistortion", "WebPSafeCalloc", "WebPPictureSmartARGBToYUVA", "WebPDecodeARGB", "WebPIUpdate", "WebPPictureImportRGBA", "WebPDecodeRGB", "WebPMemoryWriterInit", "WebPDecodeBGRInto", "WebPDecode", "WebPPictureAlloc", "_fini", "WebPPictureImportRGB", "WebPConfigLosslessPreset", "VP8CheckSignature", "WebPINewYUVA", "WebPPictureCopy", "WebPDecodeARGBInto", "WebPEncode", "WebPPictureImportBGRX", "WebPDecodeRGBAInto", "WebPMemoryWriterClear", "WebPConfigInitInternal", "WebPPictureImportBGR", "WebPDecodeRGBA", "WebPGetInfo", "WebPIAppend", "WebPGetDecoderVersion", "_init", "WebPDecodeBGR", "WebPPictureYUVAToARGB", "WebPPictureARGBToYUVADithered", "WebPFreeDecBuffer", "WebPSafeMalloc", "WebPEncodeLosslessRGB", "WebPPictureSharpARGBToYUVA", "WebPCleanupTransparentArea", "WebPCopyPlane", "WebPEncodeBGRA", "WebPValidateConfig", "WebPPictureView", "WebPMemoryWrite", "WebPDecodeYUV", "WebPDecodeBGRA", "WebPFree", "WebPGetEncoderVersion", "WebPPictureInitInternal", "VP8GetInfo", "WebPINewRGB", "WebPInitDecoderConfigInternal", "WebPEncodeRGBA", "WebPGetFeaturesInternal", "WebPPictureFree", "WebPPictureIsView", "WebPIDecodedArea", "WebPPictureCrop", "WebPDecodeBGRAInto", "WebPPictureARGBToYUVA", "WebPIDelete", "VP8LGetInfo", "WebPEncodeLosslessBGRA", "WebPDecodeYUVInto", "WebPINewYUV", "WebPINewDecoder", "WebPPictureImportBGRA", "WebPPlaneDistortion", "WebPInitDecBufferInternal"], "allstrings": ["Frame setup failed", "thread initialization failed.", "no memory during frame initialization.", "no object", "Truncated header.", "Frame not displayable.", "cannot parse picture header", "Bad code word", "bad partition length", "cannot parse segment header", "cannot parse filter header", "cannot parse partitions", "Not a key frame.", "Output aborted.", "null VP8Io passed to VP8GetHeaders()", "Incorrect keyframe parameters.", "NULL VP8Io parameter in VP8Decode().", "Premature end-of-partition0 encountered.", "Premature end-of-file encountered.", "WEBP", "VP8X", "ALPH", "VP8 ", "VP8L", "@Y>)F"], "stringidentifiers": ["WEBP", "VP8X", "ALPH", "VP8L"], "debugstrings": ["GCC: (Ubuntu 4.8.4-2ubuntu1~14.04.4) 4.8.4"], "localsymbols": ["", "YuvToRgbaRow", "PictureARGBToYUVA", "kYModesIntra4", "VP8IteratorReset", "HFilter16_SSE2", "VP8LConvertBGRAToRGBA4444", "ConvertPopulationCountTableToBitEstimates", "VP8DecodeMB", "FTransformPass1_SSE2.isra.3", "PredictorAdd11_C", "VP8GetResidualCost", "__FRAME_END__", "End", "UpsampleBgraLinePair_SSE2", "Rescale", "EmitSampledRGB", "EncodeImageNoHuffman", "order.5397", "enc_msa.c", "SetBitDepths", "Copy4x4_C", "VP8MakeLuma16Preds", "AccumulateSSE_SSE2", "lossless_neon.c", "DC8uvNoLeft_C", "BackwardReferencesLz77Box.constprop.16", "VP8DspInitSSE2", "CostManagerClear", "EmitYUV", "WebPInitConvertARGBToYUVSSE2", "__dso_handle", "VP8VFilter16i", "WebPRescalerInit", "DecodeImageData", "ExtraCostCombined_C", "RescalerImportRowExpand_SSE2", "VP8SSE8x8", "TM16_C", "HE16_SSE2", "WebPYUV444Converters", "Intra16Preds_SSE2", "HFilter8_SSE2", "VP8SetIntraUVMode", "IntraChromaPreds_C", "VP8LClearBackwardRefs", "VP8DspInit", "InitSegmentJob", "quant_levels_utils.c", "WebPRescalerExportRowExpand_C", "VP8LEncDspInit", "VP8HFilter16i", "VP8ProcessRow", "VE8uv_C", "WebPConvertRGBA32ToUV_C", "WebPMultARGBRows", "VP8LSubtractGreenFromBlueAndRed", "VP8LBitWriterResize", "Encode", "Intra16Preds_C", "ConvertRGB24ToY_SSE2", "PredictorSub3_C", "BackwardReferencesLz77.constprop.17", "VP8CoeffsProba0", "DispatchAlpha_C", "UpsampleBgrLinePair_SSE2", "GetLargeValue", "VP8LClear", "VP8LFastLog2Slow", "ApplyInverseTransforms", "ApplyAlphaMultiply_C", "VP8PredChroma8", "TransformTwo_C", "ChangeState.isra.0", "quant_enc.c", "VP8LColorIndexInverseTransformAlpha", "VP8LGetBackwardReferences", "WebPHasAlpha32b", "VP8TransformUV", "Predictor6_C", "plane_to_code_lut", "NewDecoder", "VP8EncDspInitAVX2", "SimpleHFilter16i_C", "CollectHistogram_SSE41", "webp_enc.c", "HistogramAdd_C", "HorizontalFilter_SSE2", "VP8LDecodeHeader", "kVP8Log2Range", "VP8LTransformColorInverse", "WebPConvertARGBToUV", "FinishRow", "VP8LSubtractGreenFromBlueAndRed_C", "VP8LDecodeAlphaHeader", "PredictorAdd10_SSE2", "VP8IteratorBytesToNz", "WebPRescaleNeededLines", "WebPMultRow", "VP8SetError", "ReconstructUV", "WebPInitConvertARGBToYUV", "VP8ParseProba", "VE4_SSE2", "VP8Cat4", "dec_msa.c", "WebPSharpYUVUpdateRGB", "VP8Decode", "thread_utils.c", "VFilter8i_SSE2", "AccumulateLSIM", "io_dec.c", "PackRGB_C", "FinalHuffmanCost", "PopulationCost", "crtstuff.c", "VP8DspInitNEON", "Predictor10_C", "WebPInitSamplers", "ApplyPaletteHash2", "kBiasMatrices", "EmitRescaledRGB", "VP8SSE16x8", "VP8InitDithering", "kLinearToGammaTabF", "VP8LConvertBGRAToBGR_C", "kGammaToLinearTab", "Predictor11_C", "VP8BitWriterFinish", "UpsampleRgba4444LinePair_SSE2", "GetResidualCost_SSE2", "VP8LEncDspInitMSA", "WebPInitSharpYUVSSE2", "WebPInitAlphaProcessing", "FTransformPass2_SSE2.isra.4", "WebPLogTable8bit", "Predictor12_C", "ConvertARGBToY_SSE2", "MultARGBRow_SSE2", "VP8LevelCodes", "AddGreenToBlueAndRed_SSE2", "tree_dec.c", "EmitRescaledAlphaRGB", "alpha_processing_sse2.c", "FastSLog2Slow_C", "VP8LDspInit", "AddSingle", "SmoothenBlock", "WebPConvertRGB24ToY", "kNewRange", "VP8YuvToRgba32_SSE2", "VP8LColorCacheInit", "QuantizeBlockWHT_SSE2", "upsampling_mips_dsp_r2.c", "VP8ITransform", "Upsample32Pixels_SSE2", "PredictorAdd0_SSE2", "dec_mips_dsp_r2.c", "VP8LNew", "ImportYUVAFromRGBA", "NearLosslessComponent", "DoUVTransform", "ReadImageInfo.part.11", "PredictorAdd7_SSE2", "CheckNonOpaque", "VP8LConvertBGRAToRGBA_C", "WebPPictureResetBuffers", "ConvertBGRAToRGBA4444_SSE2", "SharpYUVUpdateRGB_SSE2", "VP8LHtreeGroupsNew", "PredictorAdd12_SSE2", "TransformDC_C", "VP8SetIntra16Mode", "VP8LCollectColorBlueTransforms_C", "VP8InitResidual", "VP8IteratorExport", "VP8TransformWHT", "VE16_SSE2", "MaxDiffBetweenPixels", "WebPMultARGBRow", "VP8SetResidualCoeffs", "SharpYUVUpdateY_C", "VP8SSE4x4", "YUV420ToRGB_SSE2", "TransformColor_SSE2", "VP8DspInitMSA", "PredictorSub1_SSE2", "UpsampleRgbLinePair_SSE2", "kGammaTablesFOk", "Predictor2_C", "VP8LConvertBGRAToRGB565_C", "iterator_enc.c", "kAcTable2", "VP8IteratorProgress", "VP8FixedCostsI4", "kCodeLengthCodeOrder", "PredictorAdd9_SSE2", "SSE16x16_SSE2", "Disto4x4_SSE2", "VP8TBufferClear", "cost_mips32.c", "VP8InitFrame", "GetFeatures.part.0", "kLevelsFromDelta", "VP8PredLuma16", "VP8LPutBitsInternal", "PredictorSub2_C", "DoRemap", "backward_references_cost_enc.c", "HorizontalUnfilter_SSE2", "HE16_C", "kQuantToDitherAmp", "VP8LBitWriterSwap", "Mean16x4_SSE2", "YuvToBgraRow_SSE2", "filters.c", "VE4_C", "VFilter8i_C", "VP8ksclip2", "SubtractGreenFromBlueAndRed_SSE2", "cost_last_cpuinfo_used", "Disto16x16_C", "DispatchAlpha_SSE2", "StoreHuffmanCode", "dec_neon.c", "FinishDecoding", "VerticalUnfilter_SSE2", "VP8YuvToRgb56532_SSE2", "FTransform2_SSE2", "ExtractAlpha_SSE2", "ParseHeadersInternal", "dec_last_cpuinfo_used", "VP8SSIMGet", "HU4_C", "VP8SSE16x16", "Predictor8_SSE2", "__do_global_dtors_aux_fini_array_entry", "TBufferNewPage", "EncoderInit", "VP8EntropyCost", "VP8VFilter8", "VP8HFilter8i", "WebPAllocateDecBuffer", "MultRow_SSE2", "WebPApplyAlphaMultiply", "PredictLineLeft_SSE2", "VP8ScanUV", "ExtraCost_C", "WebPConvertARGBToY", "CollectHistogram_SSE2", "WebPReportProgress", "Reset", "VP8LInverseTransform", "DC16NoTopLeft_C", "WebPRescalerDspInitNEON", "__do_global_dtors_aux", "VP8LHtreeGroupsFree", "PredictorSub4_C", "rescaler.c", "Predictor12_SSE2", "PredictorSub11_C", "VP8LConvertBGRAToRGBA", "VP8LEncDspInitMIPSdspR2", "kFreqSharpening", "DC8uvNoTopLeft_C", "Predictor8_C", "WebPYuv444ToBgr_C", "WebPFilters", "clip1", "VP8Clear", "kCat3456", "IDecode", "VP8IteratorSetCountDown", "WebPMultRows", "cpu.c", "VP8LConvertBGRAToRGBA4444_C", "Predictor5_SSE2", "TransformOne_C", "WebPPackRGB", "PredictorAdd0_C", "AccumulateSSE_C", "VP8AdjustFilterStrength", "Disto4x4_C", "UpsampleRgb565LinePair_SSE2", "WebPInitCustomIo", "CheckDecBuffer", "sclip2", "YuvToBgraRow", "YUV444ToRGB_SSE2", "picture_tools_enc.c", "filters_sse2.c", "VP8TDisto16x16", "Init", "Predictor10_SSE2", "RescalerExportRowExpand_SSE2", "kLosslessPresets", "CombinedShannonEntropy_SSE2", "VP8LInitBitReader", "WebPInitUpsamplers", "VP8LBitWriterWipeOut", "VP8Transform", "VP8SSIMFromStatsClipped", "VP8LBuildHuffmanTable", "PostLoopFinalize", "RD4_C", "SSE16x16_C", "AddVectorEq_SSE2.constprop.3", "VP8LFreeHistogramSet", "PredictorSub6_C", "PredictorAdd5_SSE2", "VP8VFilter8i", "TM8uv_C", "rescaler_neon.c", "TTransform_SSE2", "kCodeLengthRepeatOffsets", "Flatten", "VP8LHistogramInit", "SimpleVFilter16i_SSE2", "VP8LCollectColorRedTransforms", "VP8EncDeleteAlpha", "upsampling_last_cpuinfo_used1", "vp8l_dec.c", "WebPInitSharpYUVNEON", "TransformColorInverse_SSE2", "Launch", "VP8IteratorNzToBytes", "HasAlpha32b_C", "VP8LBitWriterClone", "VP8YuvToRgba444432_SSE2", "VP8TBufferInit", "VP8EncDspCostInitMIPSdspR2", "VP8LPutBitsFlushBits", "AccumulateSSIM", "VP8EncDspInitSSE41", "VP8FiltersInitNEON", "VP8LBitEntropyInit", "UpsampleRgba4444LinePair_C", "VP8LEncoderDelete", "VP8CoeffsUpdateProba", "rescaler_last_cpuinfo_used", "Intra4Preds_SSE2", "HasAlpha8b_C", "VP8LHashChainFill", "PredictionCostCrossColor", "MapAlpha_C", "DC8uvNoTop_C", "VP8I16ModeOffsets", "enc_mips32.c", "EmitAlphaRGB", "VP8EncInitAlpha", "VP8LDistanceToPlaneCode", "ImportBlock", "ExtractAlpha_C", "ThreadLoop", "UpsampleBgrLinePair_C", "ConvertARGBToY_C", "ConvertToYUVA", "WebPRescalerExportRowShrink", "VP8SimpleHFilter16i", "DC8uv_SSE2", "TransformUV_C", "TTransform", "DitherCombine8x8_C", "VE16_C", "Yuv444ToBgra_SSE2", "VP8IteratorNext", "filters_last_cpuinfo_used", "VP8LPredictorsSub_C", "WebPYuv444ToRgb565_C", "lossless_enc_mips32.c", "TM8uv_SSE2", "histogram_enc.c", "DecodeIntoRGBABuffer", "ConvertRGB24ToY_C", "rescaler_utils.c", "DC16NoTop_C", "VP8LColorCacheCopy", "UpsampleArgbLinePair_SSE2", "VP8LEncodeStream", "random_utils.c", "ExtractPalettedAlphaRows", "VFilter16i_C", "frame_enc.c", "VP8LFreeHistogram", "ReconstructIntra4", "cost_mips_dsp_r2.c", "Transform_SSE2", "FinalizeTokenProbas", "VP8EncQuantize2Blocks", "PredictorAdd12_C", "VP8AccumulateSSE", "utils.c", "VP8SetSegmentParams", "WebPIoInitFromOptions", "Yuv444ToRgb565_SSE2", "kCat3", "VP8LDoFillBitWindow", "CustomTeardown", "kStorageOrder.5285", "ApplyPaletteHash1", "WebPEstimateBestFilter", "QuantizeLevels", "HFilter16i_SSE2", "SSIMGet_C", "Predictor9_C", "DC16NoTop_SSE2", "PredictorAdd1_SSE2", "VP8PredLuma4", "TTransform_SSE41", "kCat6", "Predictor6_SSE2", "predictor_enc.c", "Predictor13_C", "VP8EncPredLuma4", "Mean16x4_C", "Disto4x4_SSE41", "VP8LDspInitSSE2", "HistogramCombineEntropyBin", "kInvAlpha", "UpdateHistogramCost", "ApplyPaletteHash0", "kAlphabetSize", "PredictLine_C.part.0", "g_worker_interface", "WebPInitAlphaProcessingNEON", "SimpleVFilter16_C", "enc_last_cpuinfo_used", "WebPInitYUV444ConvertersSSE2", "YuvToBgrRow", "WebPRescalerExportRowShrink_C", "VP8YuvToBgra32_SSE2", "ExpandMatrix", "GetCoeffsAlt", "quant_dec.c", "Predictor1_C", "WebPMultRow_C", "WebPSamplerProcessPlane", "CombinedShannonEntropy_C", "UpsampleRgbaLinePair_SSE2", "SimpleHFilter16_C", "VP8IteratorSaveBoundary", "GetCoeffs", "WebPPictureAllocYUVA", "PredictorSub2_SSE2", "GetMBSSIM", "VP8SSIMDspInitSSE2", "VP8LResidualImage", "GradientUnfilter_C", "VP8EncDspInitMIPS32", "WebPDequantizeLevels", "PredictorSub13_SSE2", "_DYNAMIC", "EmitRescaledYUV", "VFilter16_C", "VP8IteratorIsDone", "PickBestIntra4", "VP8LHistogramAdd", "VP8EncDspCostInitSSE2", "WebPInitAlphaProcessingSSE41", "VP8SetSkip", "PredictorAdd11_SSE2", "WebPInitUpsamplersNEON", "PredictorAdd10_C", "dec_sse2.c", "VP8IteratorImport", "WebPRescalerExport", "completed.6982", "lossless_enc_sse41.c", "VerticalFilter_SSE2", "WebPInitUpsamplersSSE2", "AccumulateSSE", "filters_neon.c", "rgba_to_yuv_last_cpuinfo_used", "VectorMismatch_SSE2", "lossless_enc_last_cpuinfo_used", "tables_ok", "enc_mips_dsp_r2.c", "InitLeft", "DoSegmentsJob", "kTableSize", "DC16NoTopLeft_SSE2", "yuv_mips_dsp_r2.c", "VP8LDspInitMIPSdspR2", "VP8DspInitMIPS32", "HFilter16_C", "VP8Cat5", "Decode", "WebPConvertARGBToUV_C", "VP8LBitWriterInit", "alpha_processing_last_cpuinfo_used", "abs0", "VP8EncPredChroma8", "SetLoopParams", "kPrefixEncodeExtraBitsValue", "huffman_encode_utils.c", "VP8LHistogramStoreRefs", "VP8EncWrite", "AlphaMultiplyY", "GradientFilter_C", "VP8SetHistogramData", "cost_sse2.c", "BackwardReferences2DLocality.isra.13", "VP8LBitWriterReset", "kSLog2Table", "ApplyPalette", "VP8TopLeftI4", "WebPRescalerExportRowExpand", "lossless_enc_sse2.c", "WebPRescalerImportRowExpand", "quant_levels_dec_utils.c", "VP8LAddGreenToBlueAndRed_C", "rescaler_msa.c", "WebPGrabDecBuffer", "VP8DefaultProbas", "register_tm_clones", "delta_palettization_enc.c", "Yuv444ToRgba_SSE2", "VP8IteratorRotateI4", "kWeightY", "DC16NoLeft_SSE2", "BundleColorMap_SSE2", "WebPEncodingSetError", "VP8LAllocateHistogramSet", "ColorIndexInverseTransform_C.isra.1", "PredictorSub5_SSE2", "VP8BitWriterAppend", "ssim.c", "WebPInitYUV444Converters", "kHistoPairs.5182", "enc_sse41.c", "VP8LHashChainInit", "WebPUnfilters", "Quantize2Blocks_SSE2", "VP8InitScanline", "ClearMetadata", "MapARGB_C", "huffman_utils.c", "WebPRescalerImportRowExpand_C", "VP8UVModeOffsets", "VP8LTransformColor_C", "VP8CollectHistogram", "upsampling.c", "VP8DspInitSSE41", "WebPUpsamplers", "VP8FTransform", "DeleteIntervalList", "PaletteCompareColorsForQsort", "GetCostModeI4", "PredictorAdd4_C", "ApplyAlphaMultiply_SSE2", "kSlowModels.2265", "PredictorSub9_C", "TM16_SSE2", "kWeightTrellis", "VP8EncDspInitMIPSdspR2", "LD4_SSE2", "token_enc.c", "deregister_tm_clones", "WebPSamplers", "VP8LConvertFromBGRA", "VP8StatusMessage", "VP8LHistogramEstimateBits", "VP8Decimate", "ComputeNextQ", "kCodeLengthExtraBits", "kNorm", "VP8RecordCoeffs", "VP8EnterCritical", "VP8Copy4x4", "VP8LColorCacheClear", "VP8LHistogramAddSinglePixOrCopy", "PredictorSub7_C", "VP8SSIMDspInit", "ConvertBGR24ToY_C", "EmitAlphaRGBA4444", "UpsampleRgbLinePair_C", "kModeBpp", "lossless_enc_mips_dsp_r2.c", "PreLoopInitialize", "VP8LEncoderNew", "VP8SimpleVFilter16i", "VP8TransformDC", "BuildHuffmanTable", "VP8TDisto4x4", "VP8InitClipTables", "VP8LDecodeImage", "WebPInitAlphaProcessingMIPSdspR2", "Predictor5_C", "Predictor7_C", "ApplyFiltersAndEncode", "enc_avx2.c", "VP8EncQuantizeBlockWHT", "WebPRescalerDspInitMIPSdspR2", "PredictorAdd9_C", "ExportAlpha", "config_enc.c", "VP8DspInitMIPSdspR2", "SSE8x8_C", "bit_reader_utils.c", "VP8LBackwardRefsInit", "DispatchAlphaToGreen_SSE2", "filter_enc.c", "YuvToRgb565Row", "RescalePlane", "StoreImageToBitMask", "VP8BitReaderSetBuffer", "DecodeInto", "EncodeStreamHook", "VP8InitFilter", "VP8LBitsEntropy", "kRandomTable", "ExportAlphaRGBA4444", "WebPInitAlphaProcessingSSE2", "PredictorSub1_C", "VP8LoadFinalBytes", "__TMC_END__", "WebPSharpYUVFilterRow", "VP8LExtraCost", "WebPRescalerImportRowShrink", "VP8HFilter8", "VP8LFastSLog2Slow", "YuvToBgrRow_SSE2", "filters_msa.c", "IntraChromaPreds_SSE2", "WebPExtractAlpha", "VP8SetSegment", "vp8_dec.c", "PredictorAdd6_C", "HE16_SSE41", "kLiteralMap", "HorizontalFilter_C", "VP8EncDspCostInit", "HasAlpha8b_SSE2", "kBitMask", "DispatchAlphaToGreen_C", "PredictorAdd6_SSE2", "VP8PutSignedBits", "RescalerExportRowShrink_SSE2", "VP8SSIMGetClipped", "GetCombinedHistogramEntropy", "CoeffsProba0", "PredictorSub4_SSE2", "DC16_SSE2", "WebPCleanupTransparentAreaLossless", "VP8LBitWriterFinish", "Quantize2Blocks_C", "UpsampleBgraLinePair_C", "SSE16x8_SSE2", "PickBestUV", "VP8ResetProba", "alpha_processing.c", "YuvToRgbaRow_SSE2", "kFilterExtraRows", "VP8PutBits", "ITransform_SSE2", "VP8LConvertBGRAToRGB_C", "__JCR_END__", "VP8GetCostLuma4", "Copy16x8_C", "dec_sse41.c", "dec_clip_tables.c", "FTransformWHT_SSE2", "VP8SetIntra4Mode", "lossless_last_cpuinfo_used", "VP8DitherCombine8x8", "VP8StoreFilterStats", "DecodeImageStream", "kScan", "Predictor0_C", "ApplyAlphaMultiply_16b_C", "VP8Cat3", "VP8LGetCombinedEntropyUnrefined", "x86CPUInfo", "WebPExtractGreen", "VP8PutBit", "GradientUnfilter_SSE2", "GetPredictionCostCrossColorRed.isra.1", "InsertInterval.part.11", "enc_neon.c", "VP8LHashChainClear", "VP8LTransformColorInverse_C", "VP8LBundleColorMap_C", "filters_utils.c", "ExtractAlphaRows", "VP8LDspInitMSA", "PredictorSub13_C", "WebPSearchOptimalDeltaPalette", "VP8ParseQuant", "HistoQueuePush", "ShiftBytes", "kCat5", "VP8LDspInitNEON", "VP8LMapColor8b", "VP8LGetHistogramSize", "VP8GetSignedValue", "VP8LBundleColorMap", "TransformDCUV_C", "FTransform_SSE2", "YuvToRgbRow_SSE2", "VP8BitWriterWipeOut", "WebPRescalerExportRow", "QuantizeBlock_SSE41", "kAverageBytesPerMB", "ConvertBGR24ToY_SSE2", "kDcTable", "VP8LEncodeImage", "tree_enc.c", "ProcessRows", "VP8MakeIntra4Preds", "Predictor4_C", "VP8LevelFixedCosts", "picture_psnr_enc.c", "GetAlphaSourceRow", "kZigzag", "VP8LCollectColorRedTransforms_C", "VP8LBackwardRefsClear", "CompareHuffmanTrees", "WebPYuv444ToRgba4444_C", "SharpYUVFilterRow_SSE2", "VFilter8_C", "HE4_C", "WebPRescalerDspInit", "ReconstructRow.isra.3", "VP8DecompressAlphaRows", "VP8Status", "HFilter16i_C", "PredictorSub12_SSE2", "VP8YuvToBgr32_SSE2", "VP8LRefsCursorInit", "SimpleHFilter16_SSE2", "CoeffsUpdateProba", "Predictor7_SSE2", "VP8CalculateLevelCosts", "StoreSideInfo", "PredictorAdd2_SSE2", "VP8LPredictors", "HE8uv_C", "WebPInitSamplersMIPSdspR2", "VP8EncFinishAlpha", "VP8EncAnalyze", "PredictorAdd13_SSE2", "HD4_C", "VP8ParseIntraModeRow", "VP8EncDspInit", "Predictor11_SSE2", "VP8EncDspInitMSA", "kBModesProba", "VP8EncTokenLoop", "VP8LEncDspInitMIPS32", "Yuv444ToRgb_SSE2", "SharpYUVUpdateY_SSE2", "CompressAlphaJob", "ssim_last_cpuinfo_used", "VP8EncPredLuma16", "VP8FiltersInitMIPSdspR2", "VP8FTransformWHT", "YuvToRgbRow", "PredictorSub0_C", "UpdateChroma", "DC8uvNoTopLeft_SSE2", "VP8LEncDspInitSSE41", "VP8IteratorInit", "GetCoeffsFast", "WebPYuv444ToBgra_C", "ConvertBGRAToRGB_SSE2", "kCat4", "PutCoeffs", "WebPCopyDecBuffer", "VP8Delete", "VP8GetCostUV", "VP8LGetHistoImageSymbols", "kWeight", "WebPFlipBuffer", "ImportOneRow", "PredictorAdd8_C", "SetResidualCoeffs_C", "VP8LAllocateHistogram", "VP8InitRandom", "yuv_sse2.c", "VP8GetCostLuma16", "VP8LColorSpaceTransform", "AccumulateRGBA", "SSE4x4_C", "SSIMGetClipped_C", "RD4_SSE2", "Import", "WebPHasAlpha8b", "VP8SimpleHFilter16", "lossless_msa.c", "__frame_dummy_init_array_entry", "kGammaTablesOk", "YuvToRgba4444Row", "VP8EncDspInitNEON", "WebPInitYUV444ConvertersMIPSdspR2", "WebPRescalerDspInitMIPS32", "PredictorSub8_C", "LD4_C", "ReconstructIntra16", "lossless.c", "VP8EncDspInitSSE2", "PredictorSub10_SSE2", "WebPMultARGBRow_C", "VP8PutBitUniform", "DC8uvNoLeft_SSE2", "PickBestIntra16", "near_lossless_enc.c", "AdjustAndCheckRectangle", "Intra4Preds_C", "VP8LRefsCursorNextBlock", "yuv_last_cpuinfo_used", "VP8LBackwardRefsCursorAdd", "EmitRescaledAlphaYUV", "CalculateBestCacheSize.isra.14", "VP8CodeIntraModes", "alpha_processing_neon.c", "PredictorSub0_SSE2", "SSIMGet_SSE2", "ConvertBGRAToRGB565_SSE2", "VP8EncFreeBitWriters", "VP8GetValue", "cost_enc.c", "alpha_processing_sse41.c", "alpha_processing_mips_dsp_r2.c", "idec_dec.c", "VP8FiltersInit", "StoreGray", "CustomSetup", "GetHuffBitLengthsAndCodes.isra.11", "HFilter8_C", "VP8LConvertBGRAToRGB565", "WebPGetLinePairConverter", "PredictorAdd3_SSE2", "backward_references_enc.c", "VP8LDelete", "HFilter8i_SSE2", "Predictor13_SSE2", "rescaler_sse2.c", "WebPRescalerImportRowShrink_C", "VP8MakeChroma8Preds", "VP8VFilter16", "VP8New", "VP8LPredictorsAdd_C", "kLinearToGammaTab", "WebPInitSamplersSSE2", "PredictorAdd7_C", "Quantize2Blocks_SSE41", "WebPParseHeaders", "VP8FixedCostsUV", "CollectColorBlueTransforms_SSE2", "tmp.6093", "SetResidualCoeffs_SSE2", "WebPInitSamplersMIPS32", "picture_enc.c", "CollectHistogram_C", "upsampling_last_cpuinfo_used2", "PredictorAdd3_C", "NearLossless", "GetEntropyUnrefined_C", "WebPRescalerGetScaledDimensions", "YuvToArgbRow_SSE2", "VP8FilterStrengthFromDelta", "PredictorSub10_C", "ScaleDown", "kVP8NewRange", "PredictorSub8_SSE2", "DC16_C", "VectorMismatch_C", "kReversedBits", "GetResidualCost_C", "ClearHuffmanTreeIfOnlyOneSymbol", "Execute", "FTransform_C", "HasAlpha32b_SSE2", "Yuv444ToArgb_SSE2", "WebPResetDecParams", "VP8YuvToRgb32_SSE2", "VP8LBackwardReferencesTraceBackwards", "WebPDispatchAlphaToGreen", "yuv_mips32.c", "VP8SimpleVFilter16", "VP8RemapBitReader", "picture_csp_enc.c", "WebPInitUpsamplersMIPSdspR2", "kLog2Table", "PredictorAdd4_SSE2", "Predictor3_C", "yuv.c", "Yuv444ToRgba4444_SSE2", "kBands", "WebPDeallocateAlphaMemory", "WebPYuv444ToRgba_C", "WebPYuv444ToArgb_C", "SSE16x8_C", "VP8LConvertBGRAToRGB", "WebPCopyDecBufferPixels", "alpha_enc.c", "PredictorSub3_SSE2", "TM4_C", "VP8EncLoop", "rescaler_mips_dsp_r2.c", "WebPAvoidSlowMemory", "VE8uv_SSE2", "TransformAC3_C", "__JCR_LIST__", "VP8LVectorMismatch", "PredictorSub12_C", "CustomPut", "HFilter8i_C", "ssim_sse2.c", "SimpleVFilter16_SSE2", "VP8LBitsEntropyUnrefined", "VL4_SSE2", "UpsampleRgbaLinePair_C", "cost.c", "VR4_C", "VFilter8_SSE2", "VFilter16i_SSE2", "kCodeToPlane", "VP8FixedCostsI16", "color_cache_utils.c", "SubtractGreenFromBlueAndRed_SSE41", "CollectColorRedTransforms_SSE2", "lossless_enc_neon.c", "GradientFilter_SSE2", "VL4_C", "VP8EstimateTokenSize", "BitWriterResize", "TM4_SSE2", "VP8Mean16x4", "enc.c", "PredictionCostSpatial", "WebPRescalerImportRow", "ExtractGreen_C", "PredictorAdd1_C", "PredictorSub6_SSE2", "PredictorSub11_SSE2", "PredictorSub7_SSE2", "vp8l_enc.c", "frame_dec.c", "VP8HFilter16", "PredictorAdd2_C", "WebPSharpYUVUpdateY", "DC4_C", "VP8LMapColor32b", "VP8EmitTokens", "DC8uv_C", "VP8EncDspCostInitMIPS32", "VP8ksclip1", "VP8IteratorStartI4", "VP8DspScan", "FinalizeSkipProba", "ReadHuffmanCodes", "AddVector_SSE2.constprop.4", "WebPISetIOHooks", "VP8LDecodeAlphaImageStream", "DummyWriter", "lossless_enc.c", "VP8LExtraCostCombined", "UpsampleArgbLinePair_C", "upsampling_neon.c", "buffer_dec.c", "Yuv444ToBgr_SSE2", "PredictorAdd13_C", "dec.c", "VP8LCreateHuffmanTree", "PredictorSub5_C", "EmitAlphaYUV", "VP8kabs0", "FTransform2_C", "QuantizeBlock_SSE2", "HistogramClear", "yuv_neon.c", "VP8InitIoInternal", "HorizontalUnfilter_C", "VP8LBitReaderSetBuffer", "test_endian", "VP8IteratorSetRow", "QuantizeBlockWHT_SSE41", "VP8FiltersInitSSE2", "Disto16x16_SSE2", "kAcTable", "dec_mips32.c", "VP8LCombinedShannonEntropy", "VP8EncBands", "VFilter16_SSE2", "WebPPictureAllocARGB", "FTransformWHT_C", "VP8LHistogramCreate", "EmitFancyRGB", "SharpYUVFilterRow_C", "VP8LCreateCompressedHuffmanTree", "SSE8x8_SSE2", "_GLOBAL_OFFSET_TABLE_", "VP8FTransform2", "VP8LTransformColor", "VP8LGetEntropyUnrefined", "upsampling_msa.c", "lossless_mips_dsp_r2.c", "VP8LAddGreenToBlueAndRed", "ConvertBGRAToRGBA_SSE2", "VP8I4ModeOffsets", "VP8LPredictorsSub", "RescalerImportRowShrink_SSE2", "VP8YuvToArgb32_SSE2", "AddSingleSubGreen", "PredictorAdd5_C", "VP8ApplyNearLossless", "WebPConvertBGR24ToY", "kGammaToLinearTabF", "SSE4x4_SSE2", "VP8LEncDspInitSSE2", "YuvToArgbRow", "rescaler_mips32.c", "QuantizeBlock_C", "Predictor9_SSE2", "VP8RecordCoeffTokens", "VP8LEncDspInitNEON", "VP8BitWriterInit", "EncodeAlphaInternal", "DC8uvNoTop_SSE2", "webp_dec.c", "VerticalUnfilter_C", "ConvertRGBA32ToUV_SSE2", "SimpleVFilter16i_C", "VP8kclip1", "lossless_sse2.c", "bit_writer_utils.c", "Flush", "PredictorAdd8_SSE2", "ExtractAlpha_SSE41", "WebPYuv444ToRgb_C", "Sync", "sclip1", "WebPRescalerDspInitMSA", "AllocateTransformBuffer", "VP8Scan", "DC16NoLeft_C", "HistogramAddEval", "VP8SSIMFromStats", "WebPDispatchAlpha", "VP8Copy16x8", "WebPInitUpsamplersMSA", "UpsampleRgb565LinePair_C", "HistogramAdd_SSE2", "lossless_enc_msa.c", "VP8InitBitReader", "WebPConvertRGBA32ToUV", "alpha_dec.c", "enc_sse2.c", "GetCombinedEntropyUnrefined_C", "ConvertBGRAToBGR_SSE2", "VR4_SSE2", "PredictorSub9_SSE2", "filters_mips_dsp_r2.c", "TrellisQuantizeBlock", "kPrefixEncodeCode", "VP8TransformAC3", "syntax_enc.c", "ITransform_C", "TrueMotion_SSE2.part.9", "picture_rescale_enc.c", "Disto16x16_SSE41", "VP8EncStartAlpha", "VP8TransformDCUV", "VerticalFilter_C", "VP8ExitCritical", "FastLog2Slow_C", "AllocateInternalBuffers32b", "GetPSNR.part.0", "VP8LCollectColorBlueTransforms", "VP8FiltersInitMSA", "analysis_enc.c", "VP8GetThreadMethod", "VP8LConvertBGRAToBGR", "SharpYUVUpdateRGB_C", "MaxDiffsForRow.part.0", "WebPApplyAlphaMultiply4444", "WebPRescalerImport", "VP8LPredictorsAdd", "VP8GetHeaders", "VP8Cat6", "ConvertARGBToUV_SSE2", "Dither8x8", "SimpleHFilter16i_SSE2", "WebPRescalerDspInitSSE2", "WebPInitConvertARGBToYUVNEON", "VP8LReadBits", "CopyOrSwap", "frame_dummy", "VP8WriteProbas", "VP8LPredictors_C", "GetPredictionCostCrossColorBlue.isra.3", "VP8EncQuantizeBlock", "upsampling_sse2.c", "TransformWHT_C"], "dependencies": ["libm.so.6", "libpthread.so.0", "libc.so.6"], "elfname": "libwebp.so.7"}