{"globalvars": ["vpx_codec_vp9_dx_algo"], "importedglobals": [], "importedfunctions": ["pthread_create", "pthread_mutex_destroy", "pthread_once", "pthread_cond_signal", "pthread_mutex_lock", "memmove", "malloc", "pthread_cond_broadcast", "memset", "calloc", "free", "__stack_chk_fail", "memcpy", "pthread_cond_init", "pthread_mutex_init", "pthread_cond_destroy", "qsort", "strtol", "setjmp", "pthread_cond_wait", "vsnprintf", "getenv", "pthread_join", "pthread_mutex_unlock", "pthread_mutex_trylock", "longjmp"], "exportedfunctions": ["vpx_codec_control_", "vpx_img_wrap", "vpx_codec_version_extra_str", "vpx_codec_set_frame_buffer_functions", "vpx_codec_destroy", "vpx_img_flip", "vpx_codec_version", "vpx_img_alloc", "vpx_codec_vp9_dx", "vpx_codec_register_put_frame_cb", "vpx_codec_register_put_slice_cb", "vpx_img_set_rect", "vpx_codec_dec_init_ver", "vpx_codec_version_str", "vpx_codec_err_to_string", "vpx_codec_get_caps", "vpx_codec_error_detail", "vpx_codec_peek_stream_info", "vpx_codec_error", "vpx_codec_decode", "vpx_codec_get_frame", "vpx_codec_get_stream_info", "vpx_codec_iface_name", "vpx_codec_build_config", "vpx_img_free"], "allstrings": ["Failed to allocate lf_sync->cond", "Failed to allocate lf_sync->recon_done_mutex", "Failed to allocate lf_sync->recon_done_cond", "Failed to allocate lf_sync->lfdata", "Failed to allocate lf_sync->cur_sb_col", "Failed to allocate lf_sync->num_tiles_done", "Truncated packet or corrupt header length", "Uninitialized entropy context.", "Decode failed. Frame data header is corrupted.", "Failed to allocate pbi->tile_worker_data", "Decode failed. Frame data is corrupted.", "Invalid frame marker", "Unsupported bitstream profile", "Buffer %d does not contain a decoded frame", "Invalid frame sync code", "Keyframe / intra-only frame required to reset decoder state", "Failed to allocate pbi->row_mt_worker_data", "Invalid header size", "4:2:0 color not supported in profile 1 or 3", "Reserved bit set", "4:4:4 color not supported in profile 0 or 2", "Failed to allocate frame buffer", "Dimensions of %dx%d beyond allowed size of %dx%d.", "Failed to allocate context buffers", "Failed to allocate cm->cur_frame->mvs", "Failed to decode frame size", "Invalid frame size", "Referenced frame has invalid size", "Referenced frame has incompatible color format", "Invalid number of tile columns", "Failed to allocate row_mt_worker_data->jobq_buf", "Truncated packet", "Failed to allocate bool decoder 0", "Failed to allocate pbi->tile_workers", "Tile decoder thread creation failed", "Failed to decode tile data", "Invalid block size.", "Reference frame has invalid dimensions", "Truncated packet or corrupt tile length", "Failed to allocate bool decoder %d", "Truncated packet or corrupt tile size", "Failed to allocate pbi->lf_worker.data1", "Loop filter thread creation failed", "Invalid usage of segement feature on small blocks", "Failed to allocate row_mt_worker_data->recon_sync_mutex", "Failed to allocate row_mt_worker_data->recon_sync_cond", "Failed to allocate row_mt_worker_data->dqcoeff[plane]", "Failed to allocate row_mt_worker_data->eob[plane]", "Failed to allocate row_mt_worker_data->partition", "Failed to allocate row_mt_worker_data->recon_map", "Failed to allocate row_mt_worker_data->thread_data", "Failed to allocate cm->fc", "Failed to allocate cm->frame_contexts", "No 'last' reference frame", "Incorrect buffer dimensions", "Invalid reference frame", "Invalid reference frame map", "Unable to find free frame buffer", "WebM Project VP9 Decoder v1.8.0-191-g503cb8e63", "Invalid frame size in index", "Failed to allocate decoder", "row_mt out of range [0..1]", "lpf_opt out of range [0..1]", "Failed to initialize internal frame buffers", "v1.8.0-191-g503cb8e63", "191-g503cb8e63", "<invalid interface>", "Success", "Unspecified internal error", "Memory allocation error", "ABI version mismatch", "Codec does not implement requested capability", "Bitstream not supported by this decoder", "Bitstream required feature not supported by this decoder", "Corrupt frame detected", "Invalid parameter", "End of iterated list", "Unrecognized error code", "VPX_SIMD_CAPS", "VPX_SIMD_CAPS_MASK", "--target=arm64-android-gcc --enable-neon --enable-external-build --enable-pic --enable-realtime-only --disable-docs --disable-examples --disable-install-bins --disable-install-docs --disable-install-libs --disable-vp8 --disable-vp9-encoder --disable-webm-io --disable-libyuv --disable-runtime-cpu-detect --disable-unit-tests --size-limit=12288x12288 --enable-vp9-highbitdepth --disable-dependency-tracking"], "stringidentifiers": ["Success", "VPX_SIMD_CAPS", "VPX_SIMD_CAPS_MASK"], "debugstrings": ["ABI version mismatch", "Android (5058415 based on r339409) clang version 8.0.2 (https://android.googlesource.com/toolchain/clang 40173bab62ec746213857d083c0e8b0abb568790) (https://android.googlesource.com/toolchain/llvm 7a6618d69e7e8111e1d49dc9e7813767c5ca756a) (based on LLVM 8.0.2svn)"], "localsymbols": [""], "dependencies": ["libdl.so", "libm.so", "libc.so"], "elfname": "libvpx_2C02721A3FE67BC520CA9512E6AAE8DA5F4FF8FE24271ADFC43CDF51DBA3551F.so"}