{"globalvars": [], "importedglobals": [], "importedfunctions": ["memcpy", "memset", "snprintf", "pthread_mutex_unlock", "pthread_mutex_init", "pthread_cond_wait", "AndroidBitmap_getInfo", "free", "pthread_cond_destroy", "memmove", "malloc", "pthread_mutex_destroy", "AndroidBitmap_unlockPixels", "pthread_cond_init", "pthread_join", "pthread_cond_signal", "calloc", "AndroidBitmap_lockPixels", "pthread_create", "pthread_mutex_lock", "__stack_chk_fail"], "exportedfunctions": ["Java_com_google_android_webp_WebpDecoder_getConfig", "JNI_OnLoad", "Java_com_google_android_webp_WebpDecoder_version", "Java_com_google_android_webp_WebpDecoder_decode", "Java_com_google_android_webp_WebpDecoder_decodeInto"], "allstrings": ["Bitmap has the wrong format: %d. Needed: RGBA8", "Could not decode alpha data.", "Keep things with the @UsedByNative annotation in proguard.", "cannot parse picture header", "(II)V", "bad partition length", "com/google/android/webp/WebpDecoder$Config", "<init>", "Incorrect keyframe parameters.", "cannot parse filter header", "NULL VP8Io parameter in VP8Decode().", "no memory during frame initialization.", "java/lang/IllegalArgumentException", "null VP8Io passed to VP8GetHeaders()", "Bad code word", "Bitmap has the wrong size: %dx%d. Needed: %dx%d", "Premature end-of-partition0 encountered.", "Truncated header.", "thread initialization failed.", "java/lang/ClassNotFoundException", "java/lang/OutOfMemoryError", "cannot parse partitions", "Frame not displayable.", "Premature end-of-file encountered.", "Frame setup failed", "cannot parse segment header", "Output aborted.", "Not a key frame.", "Cannot lock pixels", "{N{N{N{N{N{N{N{N"], "stringidentifiers": [], "debugstrings": ["Android (5058415 based on r339409) clang version 8.0.2 (https://android.googlesource.com/toolchain/clang 40173bab62ec746213857d083c0e8b0abb568790) (https://android.googlesource.com/toolchain/llvm 7a6618d69e7e8111e1d49dc9e7813767c5ca756a) (based on LLVM 8.0.2svn)", "Linker: LLD 8.0.2 (https://android.googlesource.com/toolchain/lld f7e40a921051de61b8d8a2ca3af5e632a662af12)", "GCC: (GNU) 4.9.x 20150123 (prerelease)"], "localsymbols": [""], "dependencies": ["libm.so", "libjnigraphics.so", "libc.so", "libdl.so", "liblog.so"], "elfname": "libwebp_android.so"}